Nsc512/__init__.py
Nsc512/core.py
Nsc512/main.py
nsc512-1.1.0.dist-info/METADATA
nsc512-1.1.0.dist-info/WHEEL
nsc512-1.1.0.dist-info/entry_points.txt
nsc512-1.1.0.dist-info/top_level.txt
nsc512-1.1.0.dist-info/RECORD
