Metadata-Version: 2.4
Name: nsc512
Version: 1.1.0
Summary: Nsc410 增强版表达式处理器
Author-email: Your Name <your.email@example.com>
Requires-Dist: Nsc371
Provides-Extra: dev
Requires-Dist: pytest>=6.0; extra == "dev"
